{"frames": {

"botonayudadown.png":
{
	"frame": {"x":0,"y":48,"w":204,"h":54},
	"rotated": false,
	"trimmed": false,
	"spriteSourceSize": {"x":0,"y":0,"w":204,"h":54},
	"sourceSize": {"w":204,"h":54}
},
"botonayudaover.png":
{
	"frame": {"x":204,"y":48,"w":204,"h":54},
	"rotated": false,
	"trimmed": false,
	"spriteSourceSize": {"x":0,"y":0,"w":204,"h":54},
	"sourceSize": {"w":204,"h":54}
},
"botonayudaup.png":
{
	"frame": {"x":0,"y":102,"w":204,"h":54},
	"rotated": false,
	"trimmed": false,
	"spriteSourceSize": {"x":0,"y":0,"w":204,"h":54},
	"sourceSize": {"w":204,"h":54}
},
"botonjugardown.png":
{
	"frame": {"x":0,"y":156,"w":204,"h":54},
	"rotated": false,
	"trimmed": false,
	"spriteSourceSize": {"x":0,"y":0,"w":204,"h":54},
	"sourceSize": {"w":204,"h":54}
},
"botonjugarover.png":
{
	"frame": {"x":204,"y":102,"w":204,"h":54},
	"rotated": false,
	"trimmed": false,
	"spriteSourceSize": {"x":0,"y":0,"w":204,"h":54},
	"sourceSize": {"w":204,"h":54}
},
"botonjugarup.png":
{
	"frame": {"x":204,"y":156,"w":204,"h":54},
	"rotated": false,
	"trimmed": false,
	"spriteSourceSize": {"x":0,"y":0,"w":204,"h":54},
	"sourceSize": {"w":204,"h":54}
},
"botonpuntajedown.png":
{
	"frame": {"x":0,"y":264,"w":204,"h":54},
	"rotated": false,
	"trimmed": false,
	"spriteSourceSize": {"x":0,"y":0,"w":204,"h":54},
	"sourceSize": {"w":204,"h":54}
},
"botonpuntajeover.png":
{
	"frame": {"x":0,"y":210,"w":204,"h":54},
	"rotated": false,
	"trimmed": false,
	"spriteSourceSize": {"x":0,"y":0,"w":204,"h":54},
	"sourceSize": {"w":204,"h":54}
},
"botonpuntajeup.png":
{
	"frame": {"x":204,"y":210,"w":204,"h":54},
	"rotated": false,
	"trimmed": false,
	"spriteSourceSize": {"x":0,"y":0,"w":204,"h":54},
	"sourceSize": {"w":204,"h":54}
},
"num00.png":
{
	"frame": {"x":294,"y":0,"w":37,"h":48},
	"rotated": false,
	"trimmed": false,
	"spriteSourceSize": {"x":0,"y":0,"w":37,"h":48},
	"sourceSize": {"w":37,"h":48}
},
"num01.png":
{
	"frame": {"x":0,"y":0,"w":29,"h":46},
	"rotated": false,
	"trimmed": false,
	"spriteSourceSize": {"x":0,"y":0,"w":29,"h":46},
	"sourceSize": {"w":29,"h":46}
},
"num02.png":
{
	"frame": {"x":59,"y":0,"w":32,"h":47},
	"rotated": false,
	"trimmed": false,
	"spriteSourceSize": {"x":0,"y":0,"w":32,"h":47},
	"sourceSize": {"w":32,"h":47}
},
"num03.png":
{
	"frame": {"x":91,"y":0,"w":32,"h":48},
	"rotated": false,
	"trimmed": false,
	"spriteSourceSize": {"x":0,"y":0,"w":32,"h":48},
	"sourceSize": {"w":32,"h":48}
},
"num04.png":
{
	"frame": {"x":222,"y":0,"w":36,"h":47},
	"rotated": false,
	"trimmed": false,
	"spriteSourceSize": {"x":0,"y":0,"w":36,"h":47},
	"sourceSize": {"w":36,"h":47}
},
"num05.png":
{
	"frame": {"x":29,"y":0,"w":30,"h":48},
	"rotated": false,
	"trimmed": false,
	"spriteSourceSize": {"x":0,"y":0,"w":30,"h":48},
	"sourceSize": {"w":30,"h":48}
},
"num06.png":
{
	"frame": {"x":187,"y":0,"w":35,"h":48},
	"rotated": false,
	"trimmed": false,
	"spriteSourceSize": {"x":0,"y":0,"w":35,"h":48},
	"sourceSize": {"w":35,"h":48}
},
"num07.png":
{
	"frame": {"x":123,"y":0,"w":32,"h":44},
	"rotated": false,
	"trimmed": false,
	"spriteSourceSize": {"x":0,"y":0,"w":32,"h":44},
	"sourceSize": {"w":32,"h":44}
},
"num08.png":
{
	"frame": {"x":155,"y":0,"w":32,"h":47},
	"rotated": false,
	"trimmed": false,
	"spriteSourceSize": {"x":0,"y":0,"w":32,"h":47},
	"sourceSize": {"w":32,"h":47}
},
"num09.png":
{
	"frame": {"x":258,"y":0,"w":36,"h":47},
	"rotated": false,
	"trimmed": false,
	"spriteSourceSize": {"x":0,"y":0,"w":36,"h":47},
	"sourceSize": {"w":36,"h":47}
},
"su-ma-do.png":
{
	"frame": {"x":0,"y":653,"w":412,"h":90},
	"rotated": false,
	"trimmed": false,
	"spriteSourceSize": {"x":0,"y":0,"w":412,"h":90},
	"sourceSize": {"w":412,"h":90}
},
"sumado-tablero.png":
{
	"frame": {"x":0,"y":318,"w":335,"h":335},
	"rotated": false,
	"trimmed": false,
	"spriteSourceSize": {"x":0,"y":0,"w":335,"h":335},
	"sourceSize": {"w":335,"h":335}
}},
"meta": {
	"app": "http://www.codeandweb.com/texturepacker",
	"version": "1.0",
	"image": "sumadotileset.png",
	"format": "RGBA8888",
	"size": {"w":412,"h":743},
	"scale": "1",
	"smartupdate": "$TexturePacker:SmartUpdate:23d89000d9494ad61068c6a26afbdd43:2ad758a57d0d7e08f9de615cb4f66c73:841807efdc91bb1daea4707f5ad87600$"
}
}
